{
    "display": {
      "icon": {
        "id": "minecraft:glow_berries"
      },
      "title": "Lush Caves",
      "description": "Visit a lush caves",
      "frame": "task",
      "show_toast": false,
      "announce_to_chat": false,
      "hidden": false
    },
    "parent": "ma:biomes/visit_dripstone_caves",
    "criteria": {
      "visit_location": {
        "trigger": "minecraft:location",
        "conditions": {
          "player": {
            "location": {
              "biomes": "minecraft:lush_caves"
            }
          }
        }
      }
    },
    "sends_telemetry_event": true
  }